{
  "value": 1.448,
  "valuePerYear": {
    "2555": 1.245,
    "2556": 1.257,
    "2557": 1.257,
    "2558": 1.327,
    "2559": 1.261,
    "2560": 1.252,
    "2561": 1.382,
    "2562": 1.448
  },
  "minimumPoint": {
    "value": 1.245,
    "year": 2555,
    "districtId": 11,
    "districtName": "ทวีวัฒนา"
  },
  "maximumPoint": {
    "value": 1.448,
    "year": 2562,
    "districtId": 11,
    "districtName": "ทวีวัฒนา"
  },
  "budgetPerYear": {
    "2555": {
      "all": 309756100,
      "focused": 84691400
    },
    "2556": {
      "all": 292293400,
      "focused": 87593800
    },
    "2557": {
      "all": 292293400,
      "focused": 87593800
    },
    "2558": {
      "all": 306422800,
      "focused": 87464200
    },
    "2559": {
      "all": 319478100,
      "focused": 94301200
    },
    "2560": {
      "all": 340005100,
      "focused": 98681800
    },
    "2561": {
      "all": 348560840,
      "focused": 118052600
    },
    "2562": {
      "all": 359861400,
      "focused": 107251900
    }
  },
  "budgetOverall": {
    "all": 2568671140,
    "focused": 765630700
  },
  "ranked": 34,
  "rankings": [
    {
      "ranked": 38,
      "year": 2555,
      "value": 1.245
    },
    {
      "ranked": 40,
      "year": 2556,
      "value": 1.257
    },
    {
      "ranked": 40,
      "year": 2557,
      "value": 1.257
    },
    {
      "ranked": 37,
      "year": 2558,
      "value": 1.327
    },
    {
      "ranked": 41,
      "year": 2559,
      "value": 1.261
    },
    {
      "ranked": 42,
      "year": 2560,
      "value": 1.252
    },
    {
      "ranked": 39,
      "year": 2561,
      "value": 1.382
    },
    {
      "ranked": 34,
      "year": 2562,
      "value": 1.448
    }
  ]
}